odoo9_addon_stock_operating_unit-9.0.1.0.0.99.dev17-py2.7-nspkg.pth
odoo9_addon_stock_operating_unit-9.0.1.0.0.99.dev17.dist-info/METADATA
odoo9_addon_stock_operating_unit-9.0.1.0.0.99.dev17.dist-info/RECORD
odoo9_addon_stock_operating_unit-9.0.1.0.0.99.dev17.dist-info/WHEEL
odoo9_addon_stock_operating_unit-9.0.1.0.0.99.dev17.dist-info/namespace_packages.txt
odoo9_addon_stock_operating_unit-9.0.1.0.0.99.dev17.dist-info/top_level.txt
odoo_addons/stock_operating_unit/README.rst
odoo_addons/stock_operating_unit/__init__.py
odoo_addons/stock_operating_unit/__openerp__.py
odoo_addons/stock_operating_unit/hooks.py
odoo_addons/stock_operating_unit/data/stock_data.xml
odoo_addons/stock_operating_unit/demo/stock_demo.xml
odoo_addons/stock_operating_unit/model/__init__.py
odoo_addons/stock_operating_unit/model/stock.py
odoo_addons/stock_operating_unit/security/stock_security.xml
odoo_addons/stock_operating_unit/static/description/icon.png
odoo_addons/stock_operating_unit/tests/__init__.py
odoo_addons/stock_operating_unit/tests/test_stock_operating_unit.py
odoo_addons/stock_operating_unit/tests/test_stock_picking.py
odoo_addons/stock_operating_unit/tests/test_stock_security.py
odoo_addons/stock_operating_unit/view/stock.xml
